resources/font.ttf
signer_pdf/__init__.py
signer_pdf/sign_generator.py
signer_pdf/signer.py
signer_pdf/resources/font.ttf
signer_pdf-0.2.1.dist-info/LICENSE
signer_pdf-0.2.1.dist-info/METADATA
signer_pdf-0.2.1.dist-info/WHEEL
signer_pdf-0.2.1.dist-info/top_level.txt
signer_pdf-0.2.1.dist-info/RECORD
